async_pushover_client/__inti__.py
async_pushover_client/exceptions.py
async_pushover_client/main.py
async_pushover_client/settings.py
async_pushover_client/worker.py
async_pushover_client-0.1.0.dist-info/LICENSE
async_pushover_client-0.1.0.dist-info/METADATA
async_pushover_client-0.1.0.dist-info/WHEEL
async_pushover_client-0.1.0.dist-info/top_level.txt
async_pushover_client-0.1.0.dist-info/RECORD
