Metadata-Version: 2.1
Name: async-pushover-client
Version: 0.1.0
Summary: a set of methods for working with PushOver
Home-page: https://github.com/Sergey-Yalovoy/async_pushover_client
Author: Sergey Yalovoy
Author-email: sergeyyolovoi@gmail.com
Classifier: Programming Language :: Python :: 3
Classifier: License :: OSI Approved :: GNU General Public License (GPL)
Classifier: Operating System :: OS Independent
Requires-Python: >=3.8
License-File: LICENSE
Requires-Dist: aiofiles ==23.2.1
Requires-Dist: aiohttp ==3.8.5
Requires-Dist: async-websocket-client ==0.1.0
Requires-Dist: python-dotenv ==1.0.0
Requires-Dist: requests ==2.31.0
